PythonicDISORT/__init__.py
PythonicDISORT/_assemble_intensity_and_fluxes.py
PythonicDISORT/_solve_for_coeffs.py
PythonicDISORT/_solve_for_gen_and_part_sols.py
PythonicDISORT/pydisort.py
PythonicDISORT/subroutines.py
pythonicdisort-1.5.dist-info/LICENSE.md
pythonicdisort-1.5.dist-info/METADATA
pythonicdisort-1.5.dist-info/WHEEL
pythonicdisort-1.5.dist-info/top_level.txt
pythonicdisort-1.5.dist-info/RECORD
