Metadata-Version: 2.1
Name: PythonicDISORT
Version: 1.5
Summary: Discrete Ordinates Solver for the (1D) Radiative Transfer Equation in a single or multi-layer atmosphere.
Author-email: Dion HO Jia Xu <dh3065@columbia.edu>
Project-URL: Homepage, https://github.com/LDEO-CREW/Pythonic-DISORT
Classifier: Programming Language :: Python :: 3
Classifier: License :: OSI Approved :: MIT License
Classifier: Operating System :: OS Independent
Requires-Python: >=3.8
License-File: LICENSE.md
Requires-Dist: numpy >=1.8.0
Requires-Dist: scipy >=1.8.0
Provides-Extra: notebook_dependencies
Requires-Dist: autograd >=1.5 ; extra == 'notebook_dependencies'
Requires-Dist: jupyter >1.0.0 ; extra == 'notebook_dependencies'
Requires-Dist: notebook >6.5.2 ; extra == 'notebook_dependencies'
Requires-Dist: matplotlib >=3.6.0 ; extra == 'notebook_dependencies'
Provides-Extra: pytest
Requires-Dist: pytest >=6.2.5 ; extra == 'pytest'
